{
  "last-round": 693,
  "txn-groups": [
    {
      "txn-results": [
        {
          "txn-result": {
            "pool-error": "",
            "txn": {
              "txn": {
                "amt": 1500000,
                "fee": 1000,
                "fv": 693,
                "gen": "dockernet-v1",
                "gh": "XvCtvw6QXM01GeprPbNQtkhYdkK2RioEedHWIsZUPu0=",
                "grp": "LKm++L0J45nq/QAUseEwJtJ6SHLtPsk7EEqsNzGkplA=",
                "lv": 1693,
                "rcv": "i2cApBl/ZJWeCH86lgI7AGKbPvg2/hRS4G5ip9xF2Yw=",
                "snd": "kD/NYse5ghHHSxM/eQyfg2vZNpJ/JlJ5LNZkBgILpko=",
                "type": "pay"
              }
            }
          }
        },
        {
          "txn-result": {
            "pool-error": "",
            "txn": {
              "txn": {
                "apaa": [
                  "eMUsnw==",
                  "i2cApBl/ZJWeCH86lgI7AGKbPvg2/hRS4G5ip9xF2Yw=",
                  "AAAAAAAACEg=",
                  "AAAAAAAAAAM="
                ],
                "apid": 2121,
                "fee": 1000,
                "fv": 693,
                "gen": "dockernet-v1",
                "gh": "XvCtvw6QXM01GeprPbNQtkhYdkK2RioEedHWIsZUPu0=",
                "grp": "LKm++L0J45nq/QAUseEwJtJ6SHLtPsk7EEqsNzGkplA=",
                "lv": 1693,
                "snd": "i2cApBl/ZJWeCH86lgI7AGKbPvg2/hRS4G5ip9xF2Yw=",
                "type": "appl"
              }
            }
          },
          "app-budget-consumed": 47,
          "exec-trace": {
            "approval-program-hash": "jLJ0TggPWzlM5ehtsdkVNmCVPlwfsMhnFjR4hhZwVy0=",
            "approval-program-trace": [
              {
                "pc": 1
              },
              {
                "pc": 10
              },
              {
                "pc": 13,
                "stack-additions": [
                  {
                    "type": 2,
                    "uint": 2121
                  }
                ]
              },
              {
                "pc": 15,
                "stack-additions": [
                  {
                    "type": 2
                  }
                ],
                "stack-pop-count": 1
              },
              {
                "pc": 16,
                "stack-additions": [
                  {
                    "type": 2,
                    "uint": 6
                  }
                ]
              },
              {
                "pc": 18,
                "stack-additions": [
                  {
                    "type": 2
                  }
                ],
                "stack-pop-count": 2
              },
              {
                "pc": 19,
                "stack-additions": [
                  {
                    "type": 2
                  }
                ]
              },
              {
                "pc": 21,
                "stack-additions": [
                  {
                    "type": 2
                  }
                ],
                "stack-pop-count": 2
              },
              {
                "pc": 22,
                "stack-pop-count": 1
              },
              {
                "pc": 609,
                "stack-additions": [
                  {
                    "type": 1,
                    "bytes": "ak5/yg=="
                  }
                ]
              },
              {
                "pc": 615,
                "stack-additions": [
                  {
                    "type": 1,
                    "bytes": "pdf7Pg=="
                  }
                ]
              },
              {
                "pc": 621,
                "stack-additions": [
                  {
                    "type": 1,
                    "bytes": "kzUxhg=="
                  }
                ]
              },
              {
                "pc": 627,
                "stack-additions": [
                  {
                    "type": 1,
                    "bytes": "yPWD8A=="
                  }
                ]
              },
              {
                "pc": 633,
                "stack-additions": [
                  {
                    "type": 1,
                    "bytes": "eMUsnw=="
                  }
                ]
              },
              {
                "pc": 639,
                "stack-additions": [
                  {
                    "type": 1,
                    "bytes": "IfHd/w=="
                  }
                ]
              },
              {
                "pc": 645,
                "stack-additions": [
                  {
                    "type": 1,
                    "bytes": "eMUsnw=="
                  }
                ]
              },
              {
                "pc": 648,
                "stack-pop-count": 7
              },
              {
                "pc": 394,
                "stack-additions": [
                  {
                    "type": 1,
                    "bytes": "AAAAAAAAAAM="
                  }
                ]
              },
              {
                "pc": 397,
                "stack-additions": [
                  {
                    "type": 2,
                    "uint": 3
                  }
                ],
                "stack-pop-count": 1
              },
              {
                "pc": 398,
                "stack-additions": [
                  {
                    "type": 2,
                    "uint": 1
                  }
                ]
              },
              {
                "pc": 400,
                "stack-additions": [
                  {
                    "type": 2,
                    "uint": 1
                  }
                ]
              },
              {
                "pc": 401,
                "stack-additions": [
                  {
                    "type": 2
                  }
                ],
                "stack-pop-count": 2
              },
              {
                "pc": 402,
                "stack-additions": [
                  {
                    "type": 2
                  },
                  {
                    "type": 2
                  }
                ],
                "stack-pop-count": 1
              },
              {
                "pc": 403,
                "stack-additions": [
                  {
                    "type": 2,
                    "uint": 1
                  }
                ],
                "stack-pop-count": 1
              },
              {
                "pc": 405,
                "stack-additions": [
                  {
                    "type": 2,
                    "uint": 1
                  }
                ]
              },
              {
                "pc": 406,
                "stack-additions": [
                  {
                    "type": 2,
                    "uint": 1
                  }
                ],
                "stack-pop-count": 2
              },
              {
                "pc": 407,
                "stack-pop-count": 1
              },
              {
                "pc": 408,
                "stack-additions": [
                  {
                    "type": 1,
                    "bytes": "AAAAAAAACEg="
                  }
                ]
              },
              {
                "pc": 411,
                "stack-additions": [
                  {
                    "type": 2,
                    "uint": 2120
                  }
                ],
                "stack-pop-count": 1
              },
              {
                "pc": 412,
                "stack-additions": [
                  {
                    "type": 1,
                    "bytes": "i2cApBl/ZJWeCH86lgI7AGKbPvg2/hRS4G5ip9xF2Yw="
                  }
                ]
              },
              {
                "pc": 415,
                "stack-additions": [
                  {
                    "type": 1,
                    "bytes": "i2cApBl/ZJWeCH86lgI7AGKbPvg2/hRS4G5ip9xF2Yw="
                  },
                  {
                    "type": 1,
                    "bytes": "i2cApBl/ZJWeCH86lgI7AGKbPvg2/hRS4G5ip9xF2Yw="
                  }
                ],
                "stack-pop-count": 1
              },
              {
                "pc": 416,
                "stack-additions": [
                  {
                    "type": 2,
                    "uint": 32
                  }
                ],
                "stack-pop-count": 1
              },
              {
                "pc": 417,
                "stack-additions": [
                  {
                    "type": 2,
                    "uint": 32
                  }
                ]
              },
              {
                "pc": 419,
                "stack-additions": [
                  {
                    "type": 2,
                    "uint": 1
                  }
                ],
                "stack-pop-count": 2
              },
              {
                "pc": 420,
                "stack-pop-count": 1
              },
              {
                "pc": 421
              },
              {
                "pc": 426
              },
              {
                "pc": 429,
                "stack-additions": [
                  {
                    "type": 1
                  }
                ]
              },
              {
                "pc": 430,
                "stack-additions": [
                  {
                    "type": 1
                  },
                  {
                    "type": 1
                  },
                  {
                    "type": 1
                  }
                ],
                "stack-pop-count": 1
              },
              {
                "pc": 432,
                "stack-additions": [
                  {
                    "type": 2,
                    "uint": 8
                  }
                ]
              },
              {
                "pc": 433,
                "stack-additions": [
                  {
                    "type": 2,
                    "uint": 8
                  }
                ]
              },
              {
                "pc": 434,
                "stack-additions": [
                  {
                    "type": 1,
                    "bytes": "i2cApBl/ZJWeCH86lgI7AGKbPvg2/hRS4G5ip9xF2Yw="
                  }
                ]
              },
              {
                "pc": 436,
                "stack-additions": [
                  {
                    "type": 2,
                    "uint": 2120
                  }
                ]
              },
              {
                "pc": 438,
                "stack-additions": [
                  {
                    "type": 1,
                    "bytes": "AAAAAAAACEg="
                  }
                ],
                "stack-pop-count": 1
              },
              {
                "pc": 439,
                "stack-additions": [
                  {
                    "type": 1,
                    "bytes": "i2cApBl/ZJWeCH86lgI7AGKbPvg2/hRS4G5ip9xF2YwAAAAAAAAISA=="
                  }
                ],
                "stack-pop-count": 2
              },
              {
                "pc": 440,
                "stack-additions": [
                  {
                    "type": 1,
                    "bytes": "i2cApBl/ZJWeCH86lgI7AGKbPvg2/hRS4G5ip9xF2YwAAAAAAAAISA=="
                  },
                  {
                    "type": 2,
                    "uint": 8
                  },
                  {
                    "type": 2,
                    "uint": 8
                  }
                ],
                "stack-pop-count": 3
              },
              {
                "pc": 442,
                "stack-pop-count": 3
              }
            ]
          }
        }
      ],
      "app-budget-added": 700,
      "app-budget-consumed": 47,
      "failed-at": [
        1
      ],
      "failure-message": "transaction BEKPGT7XJJSL4MZGK5M4TFCCI3HTOP3SOZGVBZ2GMGPMFPWBU7FA: logic eval error: invalid Box reference 0x8b6700a4197f64959e087f3a96023b00629b3ef836fe1452e06e62a7dc45d98c0000000000000848. Details: app=2121, pc=442, opcodes=concat; cover 2; box_extract"
    }
  ],
  "version": 2,
  "eval-overrides": {
    "allow-empty-signatures": true,
    "max-log-calls": 2048,
    "max-log-size": 65536
  },
  "exec-trace-config": {
    "enable": true,
    "scratch-change": true,
    "stack-change": true,
    "state-change": true
  },
  "initial-states": {
    "app-initial-states": [
      {
        "id": 2121,
        "app-boxes": {
          "kvs": [
            {
              "key": "i2cApBl/ZJWeCH86lgI7AGKbPvg2/hRS4G5ip9xF2YwAAAAAAAAISA==",
              "value": {
                "type": 1,
                "bytes": "AAAAAAAAAAUAAAAAAAehIA=="
              }
            }
          ]
        }
      }
    ]
  }
}